{
  "workload": "incr",
  "cell": {
    "keyspace": 1000000,
    "value_size": 64,
    "dist": "uniform",
    "pipeline": 16,
    "connections": 512
  },
  "timestamp": "2026-07-10T12:44:12.861238963Z",
  "aki": {
    "target": "aki",
    "version": "unknown",
    "workload": "incr",
    "skipped": false,
    "ops": 46733328,
    "errors": 0,
    "ops_per_sec": 5840699.783986047,
    "min_us": 20.367,
    "p50_us": 1329.151,
    "p99_us": 3217.407,
    "p999_us": 5623.807,
    "nil_replies": 0,
    "err_replies": 0,
    "hit_ratio": 1,
    "value_ops_per_sec": 5840699.783986047,
    "bytes_per_sec": 203004229.39096478,
    "resp_ver": 2,
    "used_memory": 4920704,
    "bytes_per_key": 4.920704
  },
  "redis": {
    "target": "redis",
    "version": "redis 8.8.0",
    "workload": "incr",
    "skipped": false,
    "ops": 43911472,
    "errors": 0,
    "ops_per_sec": 5488006.670932788,
    "min_us": 56.366,
    "p50_us": 1475.583,
    "p99_us": 1994.751,
    "p999_us": 3129.343,
    "nil_replies": 0,
    "err_replies": 0,
    "hit_ratio": 1,
    "value_ops_per_sec": 5488006.670932788,
    "bytes_per_sec": 190754099.56446874,
    "resp_ver": 2,
    "used_memory": 5600432,
    "bytes_per_key": 5.600432,
    "maxmemory_policy": "noeviction"
  },
  "valkey": {
    "target": "valkey",
    "version": "valkey 9.1.0",
    "workload": "incr",
    "skipped": false,
    "ops": 33723168,
    "errors": 0,
    "ops_per_sec": 4214318.710038638,
    "min_us": 36.567,
    "p50_us": 1922.047,
    "p99_us": 2416.639,
    "p999_us": 3545.087,
    "nil_replies": 0,
    "err_replies": 0,
    "hit_ratio": 1,
    "value_ops_per_sec": 4214318.710038638,
    "bytes_per_sec": 146282576.35185218,
    "resp_ver": 2,
    "used_memory": 4842488,
    "bytes_per_key": 4.842488,
    "maxmemory_policy": "noeviction"
  },
  "gate": {
    "pass": false,
    "reason": "aki is 1.06x Redis, below the 2.0x bar",
    "required_speedup": 2,
    "speedup_vs_redis": 1.064266159682585,
    "speedup_vs_valkey": 1.3859179112565263,
    "tail_regressed_vs_redis": true,
    "tail_regressed_vs_valkey": true
  },
  "generator_bound": false
}
